s4dl/__init__.py
s4dl/cli.py
s4dl/presign.py
s4dl-0.4.1.dist-info/METADATA
s4dl-0.4.1.dist-info/WHEEL
s4dl-0.4.1.dist-info/entry_points.txt
s4dl-0.4.1.dist-info/RECORD
