Metadata-Version: 2.4
Name: s4dl
Version: 0.4.1
Summary: Simple async S3 downloader that handles pre-signed URLs
Project-URL: Homepage, https://github.com/yourusername/s4dl
Author: Your Name
Classifier: License :: OSI Approved :: MIT License
Classifier: Operating System :: OS Independent
Classifier: Programming Language :: Python :: 3
Requires-Python: >=3.7
Requires-Dist: aiofiles
Requires-Dist: aiohttp
Requires-Dist: tqdm
Requires-Dist: typer
